text_password_protect/__init__.py
text_password_protect-0.2.0.dist-info/AUTHORS.rst
text_password_protect-0.2.0.dist-info/LICENSE
text_password_protect-0.2.0.dist-info/METADATA
text_password_protect-0.2.0.dist-info/WHEEL
text_password_protect-0.2.0.dist-info/top_level.txt
text_password_protect-0.2.0.dist-info/RECORD
