Metadata-Version: 2.1
Name: text-password-protect
Version: 0.2.0
Summary: Protect any text with your own password
Home-page: UNKNOWN
Author: Mason Egger
Author-email: mason@masonegger.com
License: MIT license
Project-URL: Documentation, https://text-password-protect.readthedocs.io/en/latest/
Project-URL: Source, https://github.com/masonegger/text-password-protect
Keywords: text_password_protect
Platform: UNKNOWN
Classifier: Development Status :: 5 - Production/Stable
Classifier: Intended Audience :: Developers
Classifier: License :: OSI Approved :: MIT License
Classifier: Natural Language :: English
Classifier: Programming Language :: Python :: 3
Classifier: Programming Language :: Python :: 3.7
Classifier: Programming Language :: Python :: 3.8
Classifier: Programming Language :: Python :: 3.9
Classifier: Programming Language :: Python :: 3.10
Requires-Python: >=3.7
Requires-Dist: cryptography
